jinfo/__init__.py
jinfo/cli.py
jitter00_jinfo-0.2.8.dist-info/METADATA
jitter00_jinfo-0.2.8.dist-info/WHEEL
jitter00_jinfo-0.2.8.dist-info/entry_points.txt
jitter00_jinfo-0.2.8.dist-info/top_level.txt
jitter00_jinfo-0.2.8.dist-info/RECORD
