Metadata-Version: 2.4
Name: jitter00-jinfo
Version: 0.2.8
Summary: Juniper device information retrieval tool via NETCONF
Requires-Python: >=3.8
Requires-Dist: ncclient>=0.6.13
Provides-Extra: dev
Requires-Dist: pytest>=7.4.0; extra == "dev"
Requires-Dist: pytest-cov>=4.1.0; extra == "dev"
Requires-Dist: ruff>=0.1.0; extra == "dev"
Requires-Dist: safety>=2.3.0; extra == "dev"
Requires-Dist: twine>=4.0.0; extra == "dev"
